totalsum/__init__.py
totalsum/admin.py
totalsum/templates/totalsum_change_list.html
totalsum/templates/totalsum_change_list_results.html
totalsum/templatetags/__init__.py
totalsum/templatetags/totalsum.py
django_totalsum_admin_django3-1.0.0.dist-info/LICENSE
django_totalsum_admin_django3-1.0.0.dist-info/METADATA
django_totalsum_admin_django3-1.0.0.dist-info/WHEEL
django_totalsum_admin_django3-1.0.0.dist-info/top_level.txt
django_totalsum_admin_django3-1.0.0.dist-info/RECORD
